yy_data_analyzer/__init__.py
yy_data_analyzer/__main__.py
yy_data_analyzer/cli.py
yy_data_analyzer/core.py
yy_data_analyzer-0.5.dist-info/METADATA
yy_data_analyzer-0.5.dist-info/WHEEL
yy_data_analyzer-0.5.dist-info/entry_points.txt
yy_data_analyzer-0.5.dist-info/top_level.txt
yy_data_analyzer-0.5.dist-info/RECORD
